scrapy_headless/__init__.py
scrapy_headless/downloader.py
scrapy_headless/request.py
scrapy_headless-0.0.1.dist-info/LICENSE
scrapy_headless-0.0.1.dist-info/METADATA
scrapy_headless-0.0.1.dist-info/WHEEL
scrapy_headless-0.0.1.dist-info/top_level.txt
scrapy_headless-0.0.1.dist-info/RECORD
