Metadata-Version: 2.1
Name: scrapy-headless
Version: 0.0.1
Summary: Download Handler for using Scrapy with headless browsers
Home-page: https://github.com/scrapy-plugins/scrapy-headless
Author: Scrapinghub
Author-email: opensource@scrapinghub.com
Maintainer: Henrique Coura
Maintainer-email: coura.henrique@gmail.com
License: BSD
Platform: Any
Classifier: Development Status :: 3 - Alpha
Classifier: License :: OSI Approved :: BSD License
Classifier: Operating System :: OS Independent
Classifier: Programming Language :: Python
Classifier: Programming Language :: Python :: 3
Classifier: Programming Language :: Python :: 3.5
Classifier: Programming Language :: Python :: 3.6
Classifier: Programming Language :: Python :: 3.7
Classifier: Framework :: Scrapy
Classifier: Intended Audience :: Developers
Classifier: Topic :: Internet :: WWW/HTTP
Classifier: Topic :: Internet :: Proxy Servers
Classifier: Topic :: Software Development :: Libraries :: Application Frameworks
Classifier: Topic :: Software Development :: Libraries :: Python Modules
Requires-Dist: scrapy (>=1.6.0)
